assertical/__init__.py
assertical/py.typed
assertical/snapshot.py
assertical/asserts/__init__.py
assertical/asserts/generator.py
assertical/asserts/pandas.py
assertical/asserts/time.py
assertical/asserts/type.py
assertical/fake/__init__.py
assertical/fake/asyncio.py
assertical/fake/generator.py
assertical/fake/http.py
assertical/fake/sqlalchemy.py
assertical/fixtures/__init__.py
assertical/fixtures/environment.py
assertical/fixtures/fastapi.py
assertical/fixtures/generator.py
assertical/fixtures/postgres.py
assertical-0.3.1.dist-info/licenses/LICENSE.txt
assertical-0.3.1.dist-info/METADATA
assertical-0.3.1.dist-info/WHEEL
assertical-0.3.1.dist-info/top_level.txt
assertical-0.3.1.dist-info/RECORD
