Metadata-Version: 2.4
Name: assertical
Version: 0.3.1
Summary: Assertical - a modular library for helping write (async) integration/unit tests for fastapi/sqlalchemy/postgres projects
Author: Battery Storage and Grid Integration Program
Project-URL: Homepage, https://github.com/bsgip/assertical
Keywords: test,fastapi,postgres,sqlalchemy
Classifier: Development Status :: 4 - Beta
Classifier: Intended Audience :: Developers
Classifier: Topic :: Software Development :: Testing
Classifier: Framework :: FastAPI
Classifier: License :: OSI Approved :: MIT License
Classifier: Programming Language :: Python :: 3
Classifier: Programming Language :: Python :: 3.9
Classifier: Programming Language :: Python :: 3.10
Classifier: Programming Language :: Python :: 3.11
Classifier: Programming Language :: Python :: 3.12
Requires-Python: >=3.9
License-File: LICENSE.txt
Requires-Dist: pytest
Requires-Dist: pytest-asyncio
Requires-Dist: anyio
Requires-Dist: httpx
Provides-Extra: all
Requires-Dist: assertical[dev,fastapi,pandas,postgres,pydantic,xml]; extra == "all"
Provides-Extra: dev
Requires-Dist: bandit; extra == "dev"
Requires-Dist: flake8; extra == "dev"
Requires-Dist: mypy; extra == "dev"
Requires-Dist: black; extra == "dev"
Requires-Dist: coverage; extra == "dev"
Provides-Extra: fastapi
Requires-Dist: fastapi[standard]; extra == "fastapi"
Requires-Dist: asgi_lifespan; extra == "fastapi"
Requires-Dist: uvicorn; extra == "fastapi"
Provides-Extra: pandas
Requires-Dist: pandas; extra == "pandas"
Requires-Dist: pandas_stubs; extra == "pandas"
Requires-Dist: numpy; extra == "pandas"
Provides-Extra: pydantic
Requires-Dist: pydantic; extra == "pydantic"
Provides-Extra: postgres
Requires-Dist: pytest-postgresql; extra == "postgres"
Requires-Dist: psycopg; extra == "postgres"
Requires-Dist: sqlalchemy>=2.0.0; extra == "postgres"
Provides-Extra: xml
Requires-Dist: pydantic_xml[lxml]!=2.17.1; extra == "xml"
Dynamic: license-file
